paikwiki_hello_cli/__init__.py
paikwiki_hello_cli/main.py
paikwiki_hello_cli/tests/__init__.py
paikwiki_hello_cli-0.0.1.dist-info/METADATA
paikwiki_hello_cli-0.0.1.dist-info/WHEEL
paikwiki_hello_cli-0.0.1.dist-info/entry_points.txt
paikwiki_hello_cli-0.0.1.dist-info/RECORD
