Metadata-Version: 2.1
Name: paikwiki-hello-cli
Version: 0.0.1
Summary: This is a Python CLI app designed to facilitate learning how to configure Python CLI applications.
Home-page: https://github.com/paikwiki/hello-cli-with-poetry.git
Author: paikwiki
Author-email: paikwiki@gmail.com
Requires-Python: >=3.12,<4.0
Classifier: Programming Language :: Python :: 3
Classifier: Programming Language :: Python :: 3.12
Project-URL: Repository, https://github.com/paikwiki/hello-cli-with-poetry.git
